odoo8_addon_framework_agreement_requisition-8.0.1.0.0-py2.7-nspkg.pth
odoo_addons/framework_agreement_requisition/purchase_workflow.xml
odoo_addons/framework_agreement_requisition/__openerp__.py
odoo_addons/framework_agreement_requisition/__init__.py
odoo_addons/framework_agreement_requisition/README.rst
odoo_addons/framework_agreement_requisition/requisition_workflow.xml
odoo_addons/framework_agreement_requisition/view/purchase_requisition.xml
odoo_addons/framework_agreement_requisition/view/purchase_order.xml
odoo_addons/framework_agreement_requisition/i18n/framework_agreement_requisition.pot
odoo_addons/framework_agreement_requisition/model/purchase.py
odoo_addons/framework_agreement_requisition/model/purchase_requisition.py
odoo_addons/framework_agreement_requisition/model/__init__.py
odoo_addons/framework_agreement_requisition/wizard/confirm_generate_agreement.py
odoo_addons/framework_agreement_requisition/wizard/confirm_generate_agreement.xml
odoo_addons/framework_agreement_requisition/wizard/__init__.py
odoo_addons/framework_agreement_requisition/test/agreement_requisition.yml
odoo8_addon_framework_agreement_requisition-8.0.1.0.0.dist-info/top_level.txt
odoo8_addon_framework_agreement_requisition-8.0.1.0.0.dist-info/WHEEL
odoo8_addon_framework_agreement_requisition-8.0.1.0.0.dist-info/RECORD
odoo8_addon_framework_agreement_requisition-8.0.1.0.0.dist-info/metadata.json
odoo8_addon_framework_agreement_requisition-8.0.1.0.0.dist-info/DESCRIPTION.rst
odoo8_addon_framework_agreement_requisition-8.0.1.0.0.dist-info/METADATA
odoo8_addon_framework_agreement_requisition-8.0.1.0.0.dist-info/namespace_packages.txt
